print_structure.py
print_structure-0.0.5.dist-info/LICENSE
print_structure-0.0.5.dist-info/WHEEL
print_structure-0.0.5.dist-info/METADATA
print_structure-0.0.5.dist-info/RECORD
